{
    "name": "SAMURAI",
    "avatar": "https://i.discogs.com/02KNT9aOoi62bZMtYCfPWnDJ9HJVEpjBYVYcs3vyrII/rs:fit/g:sm/q:90/h:600/w:600/czM6Ly9kaXNjb2dz/LWRhdGFiYXNlLWlt/YWdlcy9BLTMyMDMw/NTctMTU5OTU2Nzcz/OS00NjIyLmpwZWc.jpeg",
    "links": [
        {
            "title": "XXX",
            "url": "url",
            "image": "url"
        },
        {
            "title": "VVV",
            "url": "url",
            "image": "url"
        }
    ],
    "socials": [
        {
            "title": "Youtube",
            "url": "url",
            "image": "url"
        },
        {
            "title": "Instagram",
            "url": "url",
            "image": "url"
        }
    ]
}